odoo8_addon_website_sale_cart_selectable-8.0.1.0.0-py2.7-nspkg.pth
odoo8_addon_website_sale_cart_selectable-8.0.1.0.0.dist-info/top_level.txt
odoo8_addon_website_sale_cart_selectable-8.0.1.0.0.dist-info/WHEEL
odoo8_addon_website_sale_cart_selectable-8.0.1.0.0.dist-info/RECORD
odoo8_addon_website_sale_cart_selectable-8.0.1.0.0.dist-info/metadata.json
odoo8_addon_website_sale_cart_selectable-8.0.1.0.0.dist-info/DESCRIPTION.rst
odoo8_addon_website_sale_cart_selectable-8.0.1.0.0.dist-info/METADATA
odoo8_addon_website_sale_cart_selectable-8.0.1.0.0.dist-info/namespace_packages.txt
odoo_addons/website_sale_cart_selectable/__openerp__.py
odoo_addons/website_sale_cart_selectable/__init__.py
odoo_addons/website_sale_cart_selectable/README.rst
odoo_addons/website_sale_cart_selectable/models/product.py
odoo_addons/website_sale_cart_selectable/models/__init__.py
odoo_addons/website_sale_cart_selectable/views/website_sale_template.xml
odoo_addons/website_sale_cart_selectable/views/product_view.xml
odoo_addons/website_sale_cart_selectable/static/description/icon.png
